{"0.2.7": ["Vincent Rabaud", "vincent.rabaud@gmail.com"], "0.2.6": ["Vincent Rabaud", "vincent.rabaud@gmail.com"], "0.2.5": ["Vincent Rabaud", "vincent.rabaud@gmail.com"], "0.2.4": ["Vincent Rabaud", "vincent.rabaud@gmail.com"], "0.2.3": ["Vincent Rabaud", "vincent.rabaud@gmail.com"], "0.3.0": ["Vincent Rabaud", "vincent.rabaud@gmail.com"], "0.3.1": ["Vincent Rabaud", "vincent.rabaud@gmail.com"], "0.4.9": ["Vincent Rabaud", "vincent.rabaud@gmail.com"], "0.4.8": ["Vincent Rabaud", "vincent.rabaud@gmail.com"], "0.4.1": ["Vincent Rabaud", "vincent.rabaud@gmail.com"], "0.4.0": ["Vincent Rabaud", "vincent.rabaud@gmail.com"], "0.4.3": ["Vincent Rabaud", "vincent.rabaud@gmail.com"], "0.4.2": ["Vincent Rabaud", "vincent.rabaud@gmail.com"], "0.4.5": ["Vincent Rabaud", "vincent.rabaud@gmail.com"], "0.4.4": ["Vincent Rabaud", "vincent.rabaud@gmail.com"], "0.4.7": ["Vincent Rabaud", "vincent.rabaud@gmail.com"], "0.4.6": ["Vincent Rabaud", "vincent.rabaud@gmail.com"], "0.4.11": ["Vincent Rabaud", "vincent.rabaud@gmail.com"], "0.4.10": ["Vincent Rabaud", "vincent.rabaud@gmail.com"], "0.4.13": ["Vincent Rabaud", "vincent.rabaud@gmail.com"], "0.4.12": ["Vincent Rabaud", "vincent.rabaud@gmail.com"], "0.4.15": ["Vincent Rabaud", "vincent.rabaud@gmail.com"], "0.4.14": ["Vincent Rabaud", "vincent.rabaud@gmail.com"], "0.4.16": ["Vincent Rabaud", "vincent.rabaud@gmail.com"], "0.5.0": ["Vincent Rabaud", "vincent.rabaud@gmail.com"]}